{
  "iterations": [
    {
      "iteration": 1,
      "startedAt": "2026-03-28T04:19:33.520Z",
      "endedAt": "2026-03-28T04:27:29.878Z",
      "durationMs": 473372,
      "agent": "opencode",
      "model": "",
      "toolsUsed": {},
      "filesModified": [
        ".ralph/ralph-opencode.config.json",
        ".ralph/ralph-tasks.md",
        "apps/demo/src/components/Section.tsx",
        "apps/demo/src/pages/AvatarPage.tsx",
        "apps/demo/src/pages/ColorsPage.tsx",
        "apps/demo/src/pages/ComponentsPage.tsx",
        "apps/demo/src/pages/CopyPage.tsx",
        "apps/demo/src/pages/IconsPage.tsx",
        "apps/demo/src/pages/MotionPage.tsx",
        "apps/demo/src/pages/OverviewPage.tsx",
        "apps/demo/src/pages/ThemesPage.tsx",
        "apps/demo/src/pages/TypographyPage.tsx",
        "apps/demo/src/pages/WhyWeBuiltPage.tsx",
        "packages/ui-web/src/index.ts",
        "apps/storybook/src/stories/page-shell.stories.tsx",
        "packages/ui-web/src/patterns/page-header.test.tsx",
        "packages/ui-web/src/patterns/page-shell.test.tsx",
        "packages/ui-web/src/patterns/page-shell.tsx",
        "packages/ui-web/src/patterns/section-header.test.tsx"
      ],
      "exitCode": 0,
      "completionDetected": false,
      "errors": []
    }
  ],
  "totalDurationMs": 473372,
  "struggleIndicators": {
    "repeatedErrors": {},
    "noProgressIterations": 0,
    "shortIterations": 0
  }
}